{
    "config": {
        "iso": "2020-08-22T02:51:56.615395",
        "timestamp": 1598064716.615395
    },
    "directory_structure": {
        "iso": "2020-08-22T02:51:56.784547",
        "timestamp": 1598064716.784547
    },
    "iana": {
        "iso": "2020-08-21T12:05:47.010161",
        "timestamp": 1598011547.010161
    },
    "psl": {
        "iso": "2020-08-21T12:05:47.077687",
        "timestamp": 1598011547.077687
    },
    "user_agents": {
        "iso": "2020-08-21T12:05:47.131574",
        "timestamp": 1598011547.131574
    }
}