{
    "config": {
        "iso": "2020-08-25T12:58:58.414673",
        "timestamp": 1598360338.414673
    },
    "directory_structure": {
        "iso": "2020-08-25T12:58:58.683269",
        "timestamp": 1598360338.683269
    },
    "iana": {
        "iso": "2020-08-24T14:20:49.978036",
        "timestamp": 1598278849.978036
    },
    "psl": {
        "iso": "2020-08-24T14:20:50.045226",
        "timestamp": 1598278850.045226
    },
    "user_agents": {
        "iso": "2020-08-24T14:20:50.189185",
        "timestamp": 1598278850.189185
    }
}