{
    "config": {
        "iso": "2020-08-27T00:15:36.578252",
        "timestamp": 1598487336.578252
    },
    "directory_structure": {
        "iso": "2020-08-27T00:15:36.811943",
        "timestamp": 1598487336.811943
    },
    "iana": {
        "iso": "2020-08-26T14:37:33.574677",
        "timestamp": 1598452653.574677
    },
    "psl": {
        "iso": "2020-08-26T14:37:33.645254",
        "timestamp": 1598452653.645254
    },
    "user_agents": {
        "iso": "2020-08-26T14:37:33.703330",
        "timestamp": 1598452653.70333
    }
}