{
    "config": {
        "iso": "2020-06-28T14:06:57.039042",
        "timestamp": 1593353217.039042
    },
    "directory_structure": {
        "iso": "2020-06-28T14:24:44.846861",
        "timestamp": 1593354284.846861
    },
    "iana": {
        "iso": "2020-06-28T03:16:49.534346",
        "timestamp": 1593314209.534346
    },
    "psl": {
        "iso": "2020-06-28T03:16:49.693991",
        "timestamp": 1593314209.693991
    },
    "user_agents": {
        "iso": "2020-06-28T03:16:49.764253",
        "timestamp": 1593314209.764253
    }
}